Workbook

Sheet 00_Portada
A1: CUEVA / OADAC - Business Plan Mínimos 300k
A2: Plan audit-ready | Horizonte: julio 2026 - diciembre 2027 | Sin escenarios alternativos
A4: Tesis de ejecución
A5: La inversión mínima de 300.000 € se orienta a convertir CUEVA/OADAC en una plataforma industrial y digital sostenible: saneamiento crítico, equipo base, salida comercial, hub operativo, producto software/telecom reforzado y pipeline 2027 con ingresos objetivo auditables.
A9: Capital mínimo necesario | D9: Facturación objetivo 2027 | G9: Valor empresa actual | J9: Valor objetivo fin 2027
A10: 300000 | D10: 2155000 | G10: 4000000 | J10: 9500000
A11: Único escenario del BP | D11: Incluye Llar de Mar 2 y KIWA/RMOOB | G11: Base: inversión histórica acumulada | J11: Rango razonado: 8,0M - 12,0M
A14: Documentos de control
A15: 01_Control_Audit | B15: Trazabilidad de versión, alcance y uso previsto.
A16: 02_Supuestos | B16: Separación dato conocido / supuesto operativo / hipótesis objetivo.
A17: 11_Ingresos_2026_2027 | B17: Calendario mensual de cobros 2026-2027 y pipeline objetivo.
A18: 12_Cuenta_Resultados | B18: P&L mensual y anual con márgenes y EBITDA.
A19: 18_Valor_Empresa_2027 | B19: Bridge de valor desde 4M€ actuales hasta cierre 2027.

Sheet 01_Control_Audit
A1: Control audit-ready
A2: Alcance, fuentes y limites del modelo
A4: Campo | B4: Contenido | C4: Tipo | D4: Responsable | E4: Evidencia requerida | F4: Estado | G4: Riesgo si no existe | H4: Acción
A5: Versión | B5: BP 300k audit-ready 2026-2027 | C5: Control documental | D5: Luis / Dirección | E5: DOCX + XLSX fechados | F5: Activo | G5: Control documental confuso | H5: Bloquear cambios sin aprobacion
A6: Alcance | B6: Plan único de mínimos con inversión 300k; sin escenarios 30k/50k | C6: Gobierno | D6: Dirección | E6: Acta interna / aprobación | F6: Pendiente | G6: Lecturas erróneas | H6: Aprobar plan
A7: Fuente datos históricos | B7: Datos aportados por dirección: Menorca, Piedrahita, deuda, socios, pipeline | C7: Input dirección | D7: Luis | E7: Carpeta evidencias | F7: Pendiente | G7: Auditoría sin soporte | H7: Adjuntar facturas/contratos
A8: Fuente proyección 2027 | B8: Pipeline objetivo y contratos/LOI a formalizar | C8: Hipótesis objetivo | D8: Dirección comercial | E8: LOI/contratos/presupuestos | F8: Parcial | G8: Ingresos no reconocibles | H8: Separar committed vs target
A9: Política de cobros | B9: Cobro por hitos: firma, fabricación, instalación, cierre | C9: Supuesto operativo | D9: Finanzas | E9: Contratos modelo | F9: Pendiente | G9: Tensión de caja | H9: Normalizar cláusulas
A10: Modelo laboral | B10: Equipo base + perfiles 2027 por gates de ingresos | C10: Supuesto operativo | D10: CEO/Finanzas | E10: Contratos/prestación servicios | F10: Pendiente | G10: Sobrecoste fijo | H10: Gates de contratación
A11: Valor empresa | B11: Base 4M€ actual; objetivo 9,5M€ fin 2027 con hitos cumplidos | C11: Hipótesis valoración | D11: Dirección | E11: Informe interno valoración | F11: Pendiente | G11: Sobrevaloración | H11: Apoyar con KPIs

Sheet 02_Supuestos
A1: Supuestos del modelo
A2: Unidades explícitas: importes en euros, meses, fechas y márgenes reales; sin confundir cifras con porcentajes
A4: ID | B4: Categoría | C4: Dato / supuesto | D4: Valor | E4: Unidad | F4: Naturaleza | G4: Fuente / comentario | H4: Impacto | I4: Validación requerida | J4: Estado
A5: S01 | B5: Capital | C5: Capital mínimo necesario | D5: 300000 | E5: € | F5: Input dirección | G5: Definido como único escenario BP | H5: Financiación de ejecución | I5: Acuerdo de inversión / préstamo / aportación | J5: Pendiente
A6: S02 | B6: Marketing | C6: Partida marketing y comunicación | D6: 18000 | E6: € | F6: Input dirección | G6: Reducida según ajuste del usuario | H6: Go-to-market septiembre 2026 | I6: Presupuesto Jacqueline/proveedores | J6: Pendiente
A7: S03 | B7: Software/IT | C7: Partida Software/IT/Telecom reforzada | D7: 78000 | E7: € | F7: Supuesto operativo | G7: Aumentada respecto a la planificacion previa para reforzar producto y salida comercial | H7: Producto robusto y escalable | I7: Presupuestos SaaS/hardware/cloud | J7: Pendiente
A8: S04 | B8: Llar de Mar 2 | C8: Facturación objetivo Llar de Mar 2 | D8: 535000 | E8: € | F8: Input dirección | G8: Actualizado por dirección | H8: Ingreso Q1-Q2 2027 | I8: Contrato / presupuesto Tash | J8: Pendiente
A9: S05 | B9: KIWA/RMOOB A | C9: Proyecto KIWA/RMOOB mayo 2027 | D9: 450000 | E9: € | F9: Hipótesis objetivo | G9: Proyecto colaborativo KIWA materia + CUEVA producto | H9: Ingreso mayo-agosto 2027 | I9: LOI/contrato | J9: Pendiente
A10: S06 | B10: KIWA/RMOOB B1 | C10: Fase 1 proyecto 800k | D10: 400000 | E10: € | F10: Hipótesis objetivo | G10: Mitad del proyecto de 800k, distribuida en H2 2027 | H10: Ingreso julio-octubre 2027 | I10: LOI/contrato | J10: Pendiente
A11: S07 | B11: KIWA/RMOOB B2 | C11: Fase 2 proyecto 800k | D11: 400000 | E11: € | F11: Hipótesis objetivo | G11: Segunda mitad del proyecto de 800k, distribuida en H2 2027 | H11: Ingreso octubre-diciembre 2027 | I11: LOI/contrato | J11: Pendiente
A12: S08 | B12: Valor empresa | C12: Valor actual de referencia | D12: 4000000 | E12: € | F12: Input dirección | G12: Base: inversión histórica acumulada / valor interno actual | H12: Bridge valoración | I12: Cap table y memoria inversión | J12: Pendiente
A13: S09 | B13: Valor empresa | C13: Valor objetivo fin 2027 | D13: 9500000 | E13: € | F13: Hipótesis objetivo | G13: Rango razonado 8M-12M con hitos cumplidos | H13: Negociación futura | I13: Informe valoración | J13: Pendiente
A14: S10 | B14: Apellicer | C14: Alquiler carpa mensual | D14: 1029 | E14: €/mes + IVA | F14: Input dirección | G14: Febrero-julio pendiente; se cubren 4 mensualidades y resto condonado | H14: Saneamiento relación local | I14: Acuerdo escrito condonación | J14: Pendiente
A15: S11 | B15: Medhi | C15: Conversión deuda a OADAC | D15: 10000 | E15: € | F15: Input dirección | G15: Reconversión en 8% de OADAC | H15: Partner personal Menorca | I15: Contrato societario | J15: Pendiente
A16: S12 | B16: Ferzohaus | C16: Deuda negociada | D16: 3500 | E16: € | F16: Input dirección | G16: Importe negociado cierre | H16: Saneamiento proveedor | I16: Acuerdo de pago | J16: Pendiente

Sheet 03_Uso_Fondos_300K
A1: Uso de fondos - 300.000 €
A2: Asignación cerrada del capital mínimo necesario. Importes en €.
A4: Bloque | B4: Importe (€) | C4: % del total | D4: Objetivo | E4: Gates de liberación | F4: Responsable | G4: Evidencia | H4: Notas auditables
A5: Equipo base julio-diciembre 2026 | B5: 114600 | C5: =B5/$B$13 | D5: Sostener equipo núcleo y ejecución | E5: Calendario mensual y roles definidos | F5: CEO/Finanzas | G5: Pestaña 05 | H5: Sueldo/coste profesional según input dirección
A6: Seguridad Social / gestoría laboral / cumplimiento | B6: 18000 | C6: =B6/$B$13 | D6: Provisión laboral y regularización de costes | E6: Contrataciones y contratos formalizados | F6: Finanzas | G6: Pestaña 06 | H6: Provisión ajustable según modalidad contractual
A7: Software / IT / telecomunicaciones / IA | B7: 78000 | C7: =B7/$B$13 | D7: Reforzar producto, plataforma, telecom, DPP/POI y salida comercial | E7: Compra por hitos y necesidades de proyecto | F7: Hernán / Santi | G7: Pestañas 08-09 | H7: Partida aumentada para robustez producto
A8: Marketing y comunicación | B8: 18000 | C8: =B8/$B$13 | D8: Salida comercial profesional septiembre 2026 | E8: Web, deck, casos y contenido listos | F8: Jacqueline / Luis | G8: Plan de marketing | H8: Partida ajustada por dirección
A9: Saneamiento deuda y cierres críticos | B9: 43400 | C9: =B9/$B$13 | D9: Cerrar fricción reputacional y operativa | E9: Acuerdos firmados con proveedores | F9: CEO/Finanzas | G9: Pestaña 04 | H9: Incluye Medhi, Apellicer, Ferzohaus y timings Piedrahita
A10: Hub OADAC / Valeriano / showroom fase 0-1 | B10: 23000 | C10: =B10/$B$13 | D10: Activar nodo operativo Menorca sin sobredimensionar | E10: Acuerdo Valeriano y layout definido | F10: Luis / Valeriano / Medhi | G10: Pestaña 14 | H10: Aprovecha aportación industrial de Valeriano
A11: Legal, auditoría, documentación y contingencia | B11: 5000 | C11: =B11/$B$13 | D11: Blindaje documental y revisión externa | E11: Checklist audit-ready | F11: Dirección | G11: Pestaña 20 | H11: Colchón limitado; debe gestionarse por gates
A12: TOTAL | B12: =SUM(B5:B11) | C12: =B12/$B$13
A13: Control capital mínimo | B13: 300000 | H13: Debe cuadrar con total de uso de fondos

Sheet 04_Deuda_Saneamiento
A1: Saneamiento de deuda y cierres críticos
A2: Tratamiento por actor: pagar, convertir, condonar, negociar o ring-fence
A4: Actor | B4: Importe bruto/referencia (€) | C4: Tratamiento | D4: Cash 2026 (€) | E4: Conversión/condonación (€) | F4: Calendario | G4: Responsable | H4: Prioridad | I4: Documento soporte | J4: Estado | K4: Comentario
A5: Medhi / Bini Aida | B5: 25000 | C5: Pagar 15k y convertir 10k en 8% OADAC | D5: 15000 | E5: 10000 | F5: Julio-agosto 2026 | G5: Luis / Ángel | H5: Muy alta | I5: Acuerdo deuda + pacto socios OADAC | J5: Pendiente | K5: Partner estratégico de personal Menorca; sustituye a Jorge como referente inicial en Menorca
A6: Ferzohaus | B6: 5500 | C6: Cierre negociado a 3,5k | D6: 3500 | E6: 2000 | F6: Julio-septiembre 2026 | G6: Luis | H6: Media-alta | I6: Acuerdo de liquidación | J6: Pendiente | K6: Cerrar sin ruido reputacional
A7: Apellicer carpa/campa | B7: 7469 | C7: Pagar 4 mensualidades con IVA y desalojar; resto condonado | D7: 4980 | E7: 2489 | F7: 2+2 pagos; salida nave | G7: Luis / Ángel | H7: Alta | I7: Acuerdo condonación + acta desalojo | J7: Pendiente | K7: 1.029 €/mes + IVA; pendiente feb-jul incluidos
A8: Limpieza/desalojo Apellicer | B8: 2500 | C8: Ejecutar limpieza final y entrega | D8: 2500 | E8: 0 | F8: Julio-agosto 2026 | G8: Luis / Medhi | H8: Alta | I8: Parte entrega / fotos | J8: Pendiente | K8: Eliminar devengo mensual
A9: Piedrahita remate obra | B9: 20400 | C9: Ring-fenced: usar cobros cliente y apoyo temporal si hay gap | D9: 4400 | E9: 16000 | F9: Julio-septiembre 2026 | G9: Luis / Jorge apoyo | H9: Muy alta | I9: Presupuesto cierre obra | J9: En marcha | K9: Cimentación, estructura y fachadas ejecutadas; saneamientos/interiores en curso; cierre mediados septiembre
A10: Otros cierres/provisiones | B10: 13020 | C10: Bolsa de negociación y documentación | D10: 13020 | E10: 0 | F10: Julio-diciembre 2026 | G10: Dirección | H10: Media | I10: Justificantes | J10: Pendiente | K10: Reserva para cierres menores y gaps de caja
A11: TOTAL | B11: =SUM(B5:B10) | D11: =SUM(D5:D10) | E11: =SUM(E5:E10)

Sheet 05_Personal
A1: Personal y costes 2026-2027
A2: Costes mensuales definidos por dirección + escalado 2027 condicionado a ingresos
A4: Perfil | B4: Rol | C4: Coste mensual base (€) | D4: Variable / objetivos | E4: FTE 2026 | F4: Mes inicio 2026 | G4: Coste jul-dic 2026 (€) | H4: FTE 2027 base | I4: Coste anual 2027 base (€) | J4: Gate crecimiento | K4: Riesgo cubierto | L4: Notas
A5: Luis | B5: CEO / producto / operaciones / apoyo software / apoyo marketing / Logistik y Tash | C5: 5000 | D5: - | E5: 1 | F5: jul-26 | G5: =C5*6 | H5: 1 | I5: =C5*12 | J5: Siempre activo | K5: Dirección integral y continuidad | L5: Input dirección
A6: Ángel | B6: Finanzas / corporate / negociación Logistik y Tash / gobierno de capital | C6: 3000 | D6: - | E6: 1 | F6: jul-26 | G6: =C6*6 | H6: 1 | I6: =C6*12 | J6: Siempre activo | K6: Gobierno financiero y corporate | L6: Input dirección
A7: Emilio Torres | B7: Atención comercial: ayuntamientos, promotoras y constructoras | C7: 1500 | D7: Objetivos comerciales; definir variable por margen cobrado | E7: 0.8 | F7: jul-26 | G7: =C7*6 | H7: 0.8 | I7: =C7*12 | J7: Pipeline comercial medible | K7: Apertura mercado | L7: Sin operaciones; fuera de Logistik/Tash
A8: Hernán | B8: CTO / CUEVA OS / arquitectura digital / plataforma | C8: 4000 | D8: - | E8: 1 | F8: jul-26 | G8: =C8*6 | H8: 1 | I8: =C8*12 | J8: Siempre activo | K8: Producto digital y escalabilidad | L8: Input dirección
A9: Santi | B9: IT / telecom / cloud / integraciones / soporte técnico | C9: 2000 | D9: - | E9: 0.8 | F9: jul-26 | G9: =C9*6 | H9: 1 | I9: =C9*12 | J9: Activar salida comercial | K9: Infraestructura y soporte | L9: Input dirección
A10: Jacqueline | B10: Marketing y comunicación | C10: 1800 | D10: - | E10: 0.7 | F10: jul-26 | G10: =C10*6 | H10: 0.8 | I10: =C10*12 | J10: Salida septiembre 2026 | K10: Narrativa, marca, captación | L10: Input mantenido
A11: Jorge García Peralta | B11: Obra / apoyo puntual / calidad / remates y soporte técnico | C11: 1800 | D11: - | E11: 0.5 | F11: jul-26 | G11: =C11*6 | H11: 0.6 | I11: =C11*12 | J11: Solo proyectos con margen | K11: Control obra puntual | L11: No referente inicial Menorca
A12: Técnico POI/DPP campo | B12: Nuevo perfil 2027: lecturas, instalación, QA campo | C12: 2200 | D12: - | E12: 0 | F12: - | G12: 0 | H12: 0.75 | I12: =C12*9 | J12: Primer contrato 2027 firmado | K12: Capacidad despliegue | L12: Alta recomendada Q2 2027
A13: DevOps / Backend junior | B13: Nuevo perfil 2027: soporte Hernán/Santi, APIs, datos | C13: 2600 | D13: - | E13: 0 | F13: - | G13: 0 | H13: 0.58 | I13: =C13*7 | J13: Ingresos software/Logistik/KIWA | K13: Velocidad producto | L13: Alta condicionada Q2-Q3
A14: Customer Success / PMO | B14: Nuevo perfil 2027: implantación clientes, documentación, seguimiento | C14: 2500 | D14: - | E14: 0 | F14: - | G14: 0 | H14: 0.5 | I14: =C14*6 | J14: Pipeline > 750k firmado | K14: Calidad implantación | L14: Alta condicionada H2
A15: TOTAL | G15: =SUM(G5:G14) | I15: =SUM(I5:I14)

Sheet 06_Seguridad_Social
A1: Seguridad Social, coste empresa y provisiones
A2: Separación de coste profesional base y provisiones. Ajustar según modalidad contractual real.
A4: Concepto | B4: Base cálculo | C4: Tipo / criterio | D4: Importe 2026 (€) | E4: Importe 2027 (€) | F4: Naturaleza | G4: Responsable | H4: Validación | I4: Estado | J4: Notas
A5: Equipo base 2026 | B5: 05_Personal!G15 | C5: Coste profesional base | D5: ='05_Personal'!G15 | E5: ='05_Personal'!I15 | F5: Input/Formula | G5: Finanzas | H5: Contratos/facturas | I5: Pendiente | J5: No incluye necesariamente SS si son autónomos/proveedores
A6: Provisión SS/gestoría 2026 | B6: Uso fondos | C6: Bolsa específica | D6: 18000 | F6: Supuesto operativo | G6: Finanzas | H6: Gestoría | I6: Pendiente | J6: Dentro de los 300k
A7: Provisión coste empresa 2027 | B7: Equipo base + hires | C7: 31% sobre perfiles laborales estimados | E7: =ROUND('05_Personal'!I15*31%,0) | F7: Supuesto operativo | G7: Finanzas | H7: Modelo laboral | I7: Pendiente | J7: Solo aplica a perfiles en nómina; ajustar al mix real
A8: Gestoría / compliance laboral | B8: Mensual | C8: 500 €/mes 2027 | E8: 6000 | F8: Supuesto operativo | G8: Finanzas | H8: Presupuesto gestoría | I8: Pendiente | J8: Puede integrarse en G&A
A9: Variable Emilio objetivos | B9: Margen cobrado | C9: Cap anual indicativo | D9: 0 | E9: 24000 | F9: Hipótesis objetivo | G9: Dirección | H9: Plan comercial | I9: Pendiente | J9: Definir por margen y cobro real; no devengar sin caja
A10: TOTAL provisiones 2026/2027 | D10: =SUM(D5:D9) | E10: =SUM(E5:E9)

Sheet 07_Equipos_Workstreams
A1: Equipos / workstreams
A2: Responsables, entregables, KPIs y dependencias
A4: Workstream | B4: Responsable principal | C4: Equipo soporte | D4: Objetivo 2026 | E4: Objetivo 2027 | F4: KPIs | G4: Dependencias | H4: Riesgo | I4: Gate | J4: Estado | K4: Notas
A5: Dirección / Gobierno | B5: Luis + Ángel | C5: Hernán / finanzas | D5: Cerrar BP 300k, deuda y gates | E5: Gobierno por KPIs y caja mensual | F5: Caja, acuerdos, hitos | G5: Capital 300k | H5: Dispersión | I5: Comité mensual | J5: Activo
A6: Producto CUEVA OS | B6: Hernán | C6: Santi / Luis | D6: Entrega comercial septiembre | E6: Escalado multi-cliente y KIWA/Logistik | F6: Uptime, demos, módulos | G6: Infra SW/HW | H6: Sobredesarrollo | I6: Release mensual | J6: Activo
A7: Infra IT / Telecom | B7: Santi | C7: Hernán | D7: Stack cloud, telecom, seguridad, devices | E7: Operación cliente y campo | F7: Disponibilidad, lecturas, incidencias | G7: Licencias y hardware | H7: Fragilidad técnica | I7: Checklist salida | J7: Activo
A8: Marketing / Go-to-market | B8: Jacqueline | C8: Luis | D8: Web, deck, casos, contenido | E8: Captación recurrente y PR | F8: Leads, reuniones, conversión | G8: Casos y demos | H8: Mensaje débil | I8: Salida sept-26 | J8: Activo
A9: Comercial institucional | B9: Emilio Torres | C9: Luis | D9: Ayuntamientos/promotoras/constructoras | E9: Pipeline territorial | F9: Reuniones, LOI, ofertas | G9: Material comercial | H9: Foco insuficiente | I9: CRM semanal | J9: Activo | K9: No operaciones
A10: Logistik / Tash | B10: Luis + Ángel | C10: Hernán si demo | D10: Negociación cliente/socio y pipeline | E10: Implementación y nuevos proyectos | F10: LOI, contrato, ingreso | G10: Producto y deuda al día | H10: Bloqueo societario | I10: Separar cliente/socio | J10: Activo | K10: Emilio fuera
A11: Hub OADAC Menorca | B11: Luis / Valeriano / Medhi | C11: Jacqueline / Santi | D11: Fase 0-1, showroom mínimo | E11: Nodo productivo y comercial | F11: Capacidad, proyectos, visitas | G11: Acuerdo Valeriano | H11: Sobrecoste | I11: Capex por fases | J11: Activo | K11: Medhi personal
A12: Calidad obra / POI | B12: Jorge apoyo puntual | C12: Medhi / Santi | D12: Piedrahita y documentación | E12: Estandarizar POI/DPP en obras | F12: No conformidades, lecturas | G12: Equipo campo | H12: Descontrol obra | I12: Plantillas QA | J12: Activo

Sheet 08_Infra_SW_HW_Telecom
A1: Infraestructura Software / Hardware / Telecomunicaciones
A2: Partida reforzada para producto, demos comerciales, campo, DPP/POI, cloud y seguridad
A4: Bloque | B4: Elemento | C4: Unidades | D4: Coste unitario (€) | E4: Coste total (€) | F4: Tipo | G4: Proyecto asociado | H4: Responsable | I4: Prioridad | J4: Mes compra | K4: Evidencia | L4: Notas
A5: Hardware equipo | B5: Portátiles workstation / desarrollo | C5: 4 | D5: 1400 | E5: =C5*D5 | F5: CAPEX | G5: Producto / software | H5: Santi | I5: Alta | J5: Jul-26 | K5: Factura/proforma | L5: Equipo desarrollo y demos
A6: Hardware campo | B6: Tablets/móviles rugged para POI | C6: 5 | D6: 650 | E6: =C6*D6 | F6: CAPEX | G6: Piedrahita / Menorca / demos | H6: Santi | I6: Alta | J6: Jul-26 | K6: Factura/proforma | L6: Lecturas y checklists campo
A7: Trazabilidad | B7: Lectores RFID/NFC/BLE / URA4/R1 | C7: 5 | D7: 2500 | E7: =C7*D7 | F7: CAPEX | G7: DPP/POI / Menorca / Logistik | H7: Hernán/Santi | I7: Muy alta | J7: Ago-26 | K7: Factura/proforma | L7: Kit validación y demo industrial
A8: Trazabilidad | B8: Chips/tags/prototipos de campo | C8: 1 | D8: 6000 | E8: =C8*D8 | F8: OPEX/CAPEX | G8: DPP/POI / demos | H8: Santi | I8: Alta | J8: Ago-26 | K8: Factura/proforma | L8: Bolsa inicial de etiquetas y consumibles
A9: Telecom | B9: Routers 5G industriales + SIMs | C9: 6 | D9: 750 | E9: =C9*D9 | F9: CAPEX/OPEX | G9: Hub / obras / demos | H9: Santi | I9: Muy alta | J9: Ago-26 | K9: Factura/proforma | L9: Conectividad campo y redundancia
A10: Telecom | B10: Edge gateways / mini servidores | C10: 4 | D10: 950 | E10: =C10*D10 | F10: CAPEX | G10: Hub / Logistik / KIWA | H10: Santi | I10: Alta | J10: Sep-26 | K10: Factura/proforma | L10: Procesamiento local y sincronización
A11: Cloud | B11: Infra cloud, storage, CI/CD y backups | C11: 12 | D11: 1100 | E11: =C11*D11 | F11: OPEX | G11: CUEVA OS | H11: Hernán | I11: Muy alta | J11: Jul-26 a Jun-27 | K11: Facturas cloud | L11: 12 meses iniciales
A12: Seguridad | B12: MDM, backup, monitorización, IAM | C12: 1 | D12: 6500 | E12: =C12*D12 | F12: OPEX | G12: CUEVA OS / audit | H12: Santi | I12: Alta | J12: Sep-26 | K12: Contrato SaaS | L12: Capa de seguridad audit-ready
A13: Producto | B13: UI/product tooling, prototyping y test | C13: 1 | D13: 7500 | E13: =C13*D13 | F13: OPEX | G13: Go-to-market | H13: Hernán/Jacqueline | I13: Media-alta | J13: Ago-26 | K13: Licencias | L13: Demo, UX, testing
A14: Integración | B14: APIs, entornos, QA y pruebas campo | C14: 1 | D14: 9300 | E14: =C14*D14 | F14: OPEX | G14: KIWA/Logistik/Hub | H14: Hernán | I14: Alta | J14: Sep-Nov 26 | K14: Hitos internos | L14: Bolsa de integración
A15: Contingencia técnica | B15: Repuestos, cableado, soportes, cajas, sensores | C15: 1 | D15: 8600 | E15: =C15*D15 | F15: CAPEX/OPEX | G15: Todos | H15: Santi | I15: Media | J15: Q4-26 | K15: Facturas | L15: No sobredimensionar
A16: TOTAL | E16: =SUM(E5:E15)

Sheet 09_Licencias_IA_SaaS
A1: Licencias IA / SaaS
A2: Subpestaña de control de licencias dentro de la partida Software/IT/Telecom
A4: Licencia / servicio | B4: Uso | C4: Usuarios | D4: Coste mensual estimado (€) | E4: Meses | F4: Coste total (€) | G4: Proyecto | H4: Responsable | I4: Criticidad | J4: Notas
A5: OpenAI/API/IA generativa | B5: Asistentes, análisis, generación documentación, productividad | C5: 4 | D5: 350 | E5: 12 | F5: =C5*D5*E5 | G5: CUEVA OS / BP / comercial | H5: Hernán/Santi | I5: Alta | J5: Controlar consumo por proyecto
A6: GitHub/Copilot/Dev tooling | B6: Desarrollo y revisión código | C6: 3 | D6: 80 | E6: 12 | F6: =C6*D6*E6 | G6: CUEVA OS | H6: Hernán | I6: Alta
A7: Cloud DB / hosting / observabilidad | B7: Backends, datos, logs, uptime | C7: 1 | D7: 900 | E7: 12 | F7: =C7*D7*E7 | G7: CUEVA OS | H7: Santi | I7: Muy alta | J7: Complementa sheet 08
A8: M365/Google Workspace | B8: Documentación, correo, colaboración | C8: 7 | D8: 35 | E8: 12 | F8: =C8*D8*E8 | G8: Equipo | H8: Ángel | I8: Media-alta
A9: CRM / pipeline | B9: Seguimiento comercial, ofertas, leads | C9: 4 | D9: 65 | E9: 12 | F9: =C9*D9*E9 | G9: Comercial | H9: Emilio/Jacqueline | I9: Alta | J9: Puede comenzar simple
A10: Diseño / web / vídeo | B10: Marketing, assets, edición | C10: 2 | D10: 120 | E10: 12 | F10: =C10*D10*E10 | G10: Marketing | H10: Jacqueline | I10: Media | J10: Dentro de 18k marketing si aplica
A11: Ciberseguridad / MDM | B11: Control dispositivos, accesos, backup | C11: 1 | D11: 260 | E11: 12 | F11: =C11*D11*E11 | G11: Seguridad | H11: Santi | I11: Alta
A12: TOTAL | F12: =SUM(F5:F11)

Sheet 10_Proyectos_Objetivos
A1: Proyectos y objetivos 2026-2027
A2: Cada línea tiene ingreso, entregable, responsable, KPI y fecha máxima de activación
A4: Proyecto / línea | B4: Tipo | C4: Ingreso objetivo (€) | D4: Inicio objetivo | E4: Fin / cierre | F4: Responsable | G4: Socios/actores | H4: Objetivo de negocio | I4: KPI principal | J4: Gate | K4: Riesgo | L4: Estado
A5: Piedrahita | B5: Obra/caso comercial | C5: 16000 | D5: Jul-26 | E5: Sep-26 | F5: Luis / Jorge apoyo | G5: Cliente / Logistik | H5: Terminar vivienda y generar caso comercial | I5: Entrega mediados septiembre | J5: Cobros ring-fenced | K5: Tensión cliente/proveedor | L5: En marcha
A6: Salida comercial CUEVA | B6: Go-to-market | C6: 0 | D6: Sep-26 | E6: Dic-26 | F6: Luis / Jacqueline | G6: Equipo | H6: Web, deck, casos, oferta y CRM | I6: Web + 20 reuniones cualificadas | J6: Producto demo estable | K6: Salida débil | L6: Pendiente
A7: Hub OADAC Valeriano | B7: Hub industrial | C7: 0 | D7: Jul-26 | E7: Dic-26 | F7: Luis / Valeriano / Medhi | G7: Valeriano Alles | H7: Nodo Menorca showroom + fabricación fase 0-1 | I7: Instalación demostrable | J7: Acuerdo Valeriano | K7: Capex sin contratos | L7: Activo
A8: Llar de Mar 2 | B8: Proyecto construcción industrializada | C8: 535000 | D8: Ene-27 | E8: Abr-27 | F8: Luis + Ángel | G8: Tash / OADAC / Valeriano / Medhi | H8: Facturación y caso industrial 25 uds | I8: 535k facturados | J8: Contrato y anticipo | K8: Coste/margen obra | L8: Objetivo
A9: Logistik implementación | B9: Cliente industrial | C9: 180000 | D9: Mar-27 | E9: Dic-27 | F9: Luis + Ángel | G9: Logistik / José Luis | H9: Primer cliente industrial entidad CUEVA OS | I9: Contrato + despliegue | J9: Separar socio/cliente | K9: Bloqueo negociación | L9: Objetivo
A10: KIWA/RMOOB A | B10: Proyecto certificación/SaaS | C10: 450000 | D10: May-27 | E10: Ago-27 | F10: Luis / Hernán | G10: KIWA / RMOOB | H10: SaaS materia + SaaS producto | I10: 450k cobrados en 4 meses | J10: LOI/contrato | K10: Dependencia consorcio | L10: Objetivo
A11: KIWA/RMOOB B1 | B11: Proyecto 800k fase 1 | C11: 400000 | D11: Jul-27 | E11: Oct-27 | F11: Luis / Hernán | G11: KIWA / RMOOB | H11: Primera mitad proyecto 800k H2 | I11: 400k distribuido H2 | J11: Contrato fase 1 | K11: Ejecución técnica | L11: Objetivo
A12: KIWA/RMOOB B2 | B12: Proyecto 800k fase 2 | C12: 400000 | D12: Oct-27 | E12: Dic-27 | F12: Luis / Hernán | G12: KIWA / RMOOB | H12: Segunda mitad proyecto 800k H2 | I12: 400k distribuido H2 | J12: Contrato fase 2 | K12: Capacidad equipo | L12: Objetivo
A13: Moolde / Plastic People / Calaf | B13: Producto/piloto | C13: 90000 | D13: May-27 | E13: Sep-27 | F13: Luis / Hernán | G13: Plastic People / Calaf | H13: Piloto encofrado inteligente plástico | I13: Piloto facturado | J13: Cofinanciación | K13: Desarrollo sin caja | L13: Objetivo
A14: Marsam / marcas producto | B14: Producto/prototipos | C14: 40000 | D14: Jun-27 | E14: Nov-27 | F14: Emilio / Luis | G14: Marsam y marcas | H14: Prototipos comerciales con CUEVA | I14: 2 prototipos pagados | J14: Presupuesto firmado | K14: Prototipo gratis | L14: Objetivo
A15: SaaS/POI/DPP recurrente | B15: Software | C15: 60000 | D15: Jul-27 | E15: Dic-27 | F15: Hernán / Santi | G15: Clientes pipeline | H15: Primer ARR/servicios recurrentes | I15: MRR inicial | J15: Contratos activos | K15: Baja adopción | L15: Objetivo

Sheet 11_Ingresos_2026_2027
A1: Proyección de ingresos y calendario de cobro
A2: Importes en €. 2027 desarrollado por proyecto y fecha máxima de entrada.
A4: Línea / proyecto | B4: Naturaleza | C4: Riesgo / confianza | D4: Jul-26 | E4: Ago-26 | F4: Sep-26 | G4: Oct-26 | H4: Nov-26 | I4: Dic-26 | J4: Ene-27 | K4: Feb-27 | L4: Mar-27 | M4: Abr-27 | N4: May-27 | O4: Jun-27 | P4: Jul-27 | Q4: Ago-27 | R4: Sep-27 | S4: Oct-27 | T4: Nov-27 | U4: Dic-27 | V4: Total
A5: Piedrahita remate y cierre | B5: Cobro cliente ring-fenced | C5: Alto - obra en marcha | D5: 0 | E5: 0 | F5: 16000 | G5: 0 | H5: 0 | I5: 0 | J5: 0 | K5: 0 | L5: 0 | M5: 0 | N5: 0 | O5: 0 | P5: 0 | Q5: 0 | R5: 0 | S5: 0 | T5: 0 | U5: 0 | V5: =SUM(D5:U5)
A6: Llar de Mar 2 | B6: Proyecto construcción industrializada | C6: Medio - contrato objetivo | D6: 0 | E6: 0 | F6: 0 | G6: 0 | H6: 0 | I6: 0 | J6: 100000 | K6: 150000 | L6: 150000 | M6: 135000 | N6: 0 | O6: 0 | P6: 0 | Q6: 0 | R6: 0 | S6: 0 | T6: 0 | U6: 0 | V6: =SUM(D6:U6)
A7: Logistik implementación / CUEVA OS | B7: Cliente industrial | C7: Medio - negociación activa | D7: 0 | E7: 0 | F7: 0 | G7: 0 | H7: 0 | I7: 0 | J7: 0 | K7: 0 | L7: 25000 | M7: 25000 | N7: 25000 | O7: 25000 | P7: 25000 | Q7: 25000 | R7: 30000 | S7: 0 | T7: 0 | U7: 0 | V7: =SUM(D7:U7)
A8: KIWA/RMOOB A 450k | B8: SaaS materia + producto | C8: Medio - LOI necesario | D8: 0 | E8: 0 | F8: 0 | G8: 0 | H8: 0 | I8: 0 | J8: 0 | K8: 0 | L8: 0 | M8: 0 | N8: 112500 | O8: 112500 | P8: 112500 | Q8: 112500 | R8: 0 | S8: 0 | T8: 0 | U8: 0 | V8: =SUM(D8:U8)
A9: KIWA/RMOOB B1 400k | B9: Fase 1 proyecto 800k | C9: Medio - faseable H2 2027 | D9: 0 | E9: 0 | F9: 0 | G9: 0 | H9: 0 | I9: 0 | J9: 0 | K9: 0 | L9: 0 | M9: 0 | N9: 0 | O9: 0 | P9: 160000 | Q9: 80000 | R9: 80000 | S9: 80000 | T9: 0 | U9: 0 | V9: =SUM(D9:U9)
A10: KIWA/RMOOB B2 400k | B10: Fase 2 proyecto 800k | C10: Medio - faseable H2 2027 | D10: 0 | E10: 0 | F10: 0 | G10: 0 | H10: 0 | I10: 0 | J10: 0 | K10: 0 | L10: 0 | M10: 0 | N10: 0 | O10: 0 | P10: 0 | Q10: 0 | R10: 0 | S10: 160000 | T10: 120000 | U10: 120000 | V10: =SUM(D10:U10)
A11: Moolde / Plastic People / Calaf | B11: Piloto producto | C11: Medio-bajo - cofinanciación | D11: 0 | E11: 0 | F11: 0 | G11: 0 | H11: 0 | I11: 0 | J11: 0 | K11: 0 | L11: 0 | M11: 0 | N11: 20000 | O11: 25000 | P11: 25000 | Q11: 20000 | R11: 0 | S11: 0 | T11: 0 | U11: 0 | V11: =SUM(D11:U11)
A12: Marsam / marcas producto | B12: Prototipos comerciales | C12: Medio-bajo | D12: 0 | E12: 0 | F12: 0 | G12: 0 | H12: 0 | I12: 0 | J12: 0 | K12: 0 | L12: 0 | M12: 0 | N12: 0 | O12: 10000 | P12: 0 | Q12: 0 | R12: 15000 | S12: 0 | T12: 15000 | U12: 0 | V12: =SUM(D12:U12)
A13: SaaS/POI/DPP recurrente | B13: MRR/servicios recurrentes | C13: Medio-bajo - depende adopción | D13: 0 | E13: 0 | F13: 0 | G13: 0 | H13: 0 | I13: 0 | J13: 0 | K13: 0 | L13: 0 | M13: 0 | N13: 0 | O13: 0 | P13: 10000 | Q13: 10000 | R13: 10000 | S13: 10000 | T13: 10000 | U13: 10000 | V13: =SUM(D13:U13)
A14: TOTAL INGRESOS | D14: =SUM(D5:D13) | E14: =SUM(E5:E13) | F14: =SUM(F5:F13) | G14: =SUM(G5:G13) | H14: =SUM(H5:H13) | I14: =SUM(I5:I13) | J14: =SUM(J5:J13) | K14: =SUM(K5:K13) | ... V14: =SUM(V5:V13)

Sheet 12_Cuenta_Resultados
A1: Cuenta de resultados 2026-2027
A2: P&L mensual y anual. Importes en €. Margen directo por línea en supuestos auditables.
A4: Concepto | B4: Jul-26 | C4: Ago-26 | D4: Sep-26 | E4: Oct-26 | F4: Nov-26 | G4: Dic-26 | H4: Ene-27 | I4: Feb-27 | J4: Mar-27 | K4: Abr-27 | L4: May-27 | M4: Jun-27 | N4: Jul-27 | O4: Ago-27 | P4: Sep-27 | Q4: Oct-27 | R4: Nov-27 | S4: Dic-27 | T4: Total
A5: Ingresos | B5: ='11_Ingresos_2026_2027'!D$14 | C5: ='11_Ingresos_2026_2027'!E$14 | D5: ='11_Ingresos_2026_2027'!F$14 | E5: ='11_Ingresos_2026_2027'!G$14 | F5: ='11_Ingresos_2026_2027'!H$14 | G5: ='11_Ingresos_2026_2027'!I$14 | H5: ='11_Ingresos_2026_2027'!J$14 | I5: ='11_Ingresos_2026_2027'!K$14 | ... S5: ='11_Ingresos_2026_2027'!U$14 | T5: =SUM(B5:S5)
A6: Costes directos proyectos | B6: =ROUND(B5*55%,0) | C6: =ROUND(C5*55%,0) | D6: =ROUND(D5*55%,0) | E6: =ROUND(E5*55%,0) | F6: =ROUND(F5*55%,0) | G6: =ROUND(G5*55%,0) | H6: =ROUND(H5*55%,0) | I6: =ROUND(I5*55%,0) | ... S6: =ROUND(S5*55%,0) | T6: =SUM(B6:S6)
A7: Margen bruto | B7: =B5-B6 | C7: =C5-C6 | D7: =D5-D6 | E7: =E5-E6 | F7: =F5-F6 | G7: =G5-G6 | H7: =H5-H6 | I7: =I5-I6 | ... S7: =S5-S6 | T7: =SUM(B7:S7)
A8: % margen bruto | B8: =IFERROR(B7/B5,0) | C8: =IFERROR(C7/C5,0) | D8: =IFERROR(D7/D5,0) | E8: =IFERROR(E7/E5,0) | F8: =IFERROR(F7/F5,0) | G8: =IFERROR(G7/G5,0) | H8: =IFERROR(H7/H5,0) | I8: =IFERROR(I7/I5,0) | ... T8: =IFERROR(T7/T5,0)
A9: Personal base | B9: 19100 | C9: 19100 | D9: 19100 | E9: 19100 | F9: 19100 | G9: 19100 | H9: 19100 | I9: 19100 | J9: 19100 | K9: 21300 | L9: 21300 | M9: 21300 | N9: 23900 | O9: 23900 | P9: 23900 | Q9: 26400 | R9: 26400 | S9: 26400 | T9: =SUM(B9:S9)
A10: Seguridad Social / cumplimiento | B10: 3000 | C10: 3000 | D10: 3000 | E10: 3000 | F10: 3000 | G10: 3000 | H10: 5921 | I10: 5921 | J10: 5921 | K10: 6603 | L10: 6603 | M10: 6603 | N10: 7409 | O10: 7409 | P10: 7409 | Q10: 8184 | R10: 8184 | S10: 8184 | T10: =SUM(B10:S10)
A11: Software/IT/Telecom OPEX | B11: 8000 | C11: 8000 | D11: 8000 | E11: 11000 | F11: 11000 | G11: 11000 | H11: 6000 | I11: 6000 | J11: 6000 | K11: 6000 | L11: 6000 | M11: 6000 | N11: 8000 | O11: 8000 | P11: 8000 | Q11: 8000 | R11: 8000 | S11: 8000 | T11: =SUM(B11:S11)
A12: Marketing/Comercial | B12: 3000 | C12: 3000 | D12: 3000 | E12: 3000 | F12: 3000 | G12: 3000 | H12: 4000 | I12: 4000 | J12: 4000 | K12: 4000 | L12: 4000 | M12: 4000 | N12: 6000 | O12: 6000 | P12: 6000 | Q12: 6000 | R12: 6000 | S12: 6000 | T12: =SUM(B12:S12)
A13: G&A / legal / auditoría | B13: 1000 | C13: 1000 | D13: 1000 | E13: 1000 | F13: 1000 | G13: 1000 | H13: 2500 | I13: 2500 | J13: 2500 | K13: 2500 | L13: 2500 | M13: 2500 | N13: 2500 | O13: 2500 | P13: 2500 | Q13: 2500 | R13: 2500 | S13: 2500 | T13: =SUM(B13:S13)
A14: EBITDA | B14: =B7-SUM(B9:B13) | C14: =C7-SUM(C9:C13) | D14: =D7-SUM(D9:D13) | E14: =E7-SUM(E9:E13) | F14: =F7-SUM(F9:F13) | G14: =G7-SUM(G9:G13) | H14: =H7-SUM(H9:H13) | I14: =I7-SUM(I9:I13) | ... S14: =S7-SUM(S9:S13) | T14: =SUM(B14:S14)
A15: % EBITDA | B15: =IFERROR(B14/B5,0) | C15: =IFERROR(C14/C5,0) | D15: =IFERROR(D14/D5,0) | E15: =IFERROR(E14/E5,0) | F15: =IFERROR(F14/F5,0) | G15: =IFERROR(G14/G5,0) | H15: =IFERROR(H14/H5,0) | I15: =IFERROR(I14/I5,0) | ... T15: =IFERROR(T14/T5,0)

Sheet 13_Caja_Mensual
A1: Caja mensual
A2: Capital 300k + cobros + pagos operativos. Objetivo: autosostenibilidad con recursos propios durante 2027.
A4: Concepto | B4: Jul-26 | C4: Ago-26 | D4: Sep-26 | E4: Oct-26 | F4: Nov-26 | G4: Dic-26 | H4: Ene-27 | I4: Feb-27 | J4: Mar-27 | K4: Abr-27 | L4: May-27 | M4: Jun-27 | N4: Jul-27 | O4: Ago-27 | P4: Sep-27 | Q4: Oct-27 | R4: Nov-27 | S4: Dic-27 | T4: Total
A5: Caja inicial | B5: 0 | C5: =B10 | D5: =C10 | E5: =D10 | F5: =E10 | G5: =F10 | H5: =G10 | I5: =H10 | J5: =I10 | ... S5: =R10 | T5: =S5
A6: Aportación capital 300k | B6: 300000 | C6: 0 | D6: 0 | E6: 0 | F6: 0 | G6: 0 | H6: 0 | I6: 0 | J6: 0 | K6: 0 | L6: 0 | M6: 0 | N6: 0 | O6: 0 | P6: 0 | Q6: 0 | R6: 0 | S6: 0 | T6: =SUM(B6:S6)
A7: Cobros de clientes | B7: ='11_Ingresos_2026_2027'!D$14 | C7: ='11_Ingresos_2026_2027'!E$14 | D7: ='11_Ingresos_2026_2027'!F$14 | E7: ='11_Ingresos_2026_2027'!G$14 | F7: ='11_Ingresos_2026_2027'!H$14 | G7: ='11_Ingresos_2026_2027'!I$14 | H7: ='11_Ingresos_2026_2027'!J$14 | I7: ='11_Ingresos_2026_2027'!K$14 | ... S7: ='11_Ingresos_2026_2027'!U$14 | T7: =SUM(B7:S7)
A8: Uso de fondos 300k | B8: 65000 | C8: 55000 | D8: 60000 | E8: 45000 | F8: 40000 | G8: 35000 | H8: 0 | I8: 0 | J8: 0 | K8: 0 | L8: 0 | M8: 0 | N8: 0 | O8: 0 | P8: 0 | Q8: 0 | R8: 0 | S8: 0 | T8: =SUM(B8:S8)
A9: Costes operativos 2027 | B9: 0 | C9: 0 | D9: 0 | E9: 0 | F9: 0 | G9: 0 | H9: ='12_Cuenta_Resultados'!H6+SUM('12_Cuenta_Resultados'!H9:H13) | I9: ='12_Cuenta_Resultados'!I6+SUM('12_Cuenta_Resultados'!I9:I13) | J9: ='12_Cuenta_Resultados'!J6+SUM('12_Cuenta_Resultados'!J9:J13) | K9: ='12_Cuenta_Resultados'!K6+SUM('12_Cuenta_Resultados'!K9:K13) | L9: ='12_Cuenta_Resultados'!L6+SUM('12_Cuenta_Resultados'!L9:L13) | M9: ='12_Cuenta_Resultados'!M6+SUM('12_Cuenta_Resultados'!M9:M13) | N9: ='12_Cuenta_Resultados'!N6+SUM('12_Cuenta_Resultados'!N9:N13) | O9: ='12_Cuenta_Resultados'!O6+SUM('12_Cuenta_Resultados'!O9:O13) | ... S9: ='12_Cuenta_Resultados'!S6+SUM('12_Cuenta_Resultados'!S9:S13) | T9: =SUM(B9:S9)
A10: Caja final | B10: =B5+B6+B7-B8-B9 | C10: =C5+C6+C7-C8-C9 | D10: =D5+D6+D7-D8-D9 | E10: =E5+E6+E7-E8-E9 | F10: =F5+F6+F7-F8-F9 | G10: =G5+G6+G7-G8-G9 | H10: =H5+H6+H7-H8-H9 | I10: =I5+I6+I7-I8-I9 | ... S10: =S5+S6+S7-S8-S9 | T10: =S10
A11: Caja mínima objetivo | B11: 15000 | C11: 15000 | D11: 15000 | E11: 15000 | F11: 15000 | G11: 15000 | H11: 15000 | I11: 15000 | J11: 15000 | K11: 15000 | L11: 15000 | M11: 15000 | N11: 15000 | O11: 15000 | P11: 15000 | Q11: 15000 | R11: 15000 | S11: 15000 | T11: =S11
A12: Gap / colchón | B12: =B10-B11 | C12: =C10-C11 | D12: =D10-D11 | E12: =E10-E11 | F12: =F10-F11 | G12: =G10-G11 | H12: =H10-H11 | I12: =I10-I11 | ... S12: =S10-S11 | T12: =S12

Sheet 14_Modelo_Hub_OADAC
A1: Modelo Hub OADAC / Valeriano / Medhi
A2: Nodo industrial ligero, faseado y orientado a ventas: no sobredimensionar antes de contratos
A4: Capa | B4: Actor | C4: Aporta | D4: CUEVA/OADAC aporta | E4: Objetivo 2026 | F4: Objetivo 2027 | G4: Modelo económico | H4: Riesgo | I4: Gate | J4: Evidencia
A5: Instalaciones | B5: Valeriano Alles | C5: Naves, pistas, campas, hormigón, excavaciones, camiones, grúa | D5: Método, producto, DPP/POI, operación comercial | E5: Acuerdo marco + layout showroom | F5: Nodo Menorca operativo para proyectos | G5: Pago/uso por proyecto o acuerdo de colaboración | H5: Invertir sin contratos | I5: Acuerdo firmado | J5: Contrato/LOI
A6: Personal | B6: Medhi / Bini Aida | C6: Equipo humano y capacidad de montaje/terminaciones | D6: Integración OADAC, pipeline y metodología | E6: Reconversión 10k deuda en 8% OADAC | F6: Partner estratégico personal Menorca | G6: Participación + contratación por proyecto | H6: Confusión proveedor/socio | I6: Pacto socios OADAC | J6: Acuerdo societario
A7: Tecnología | B7: CUEVA | C7: CUEVA OS, DPP, POI, interfaces, trazabilidad | D7: Licencia y control de producto | E7: Demo y stack estable | F7: Producto escalable multi-cliente | G7: Licencia/fee/servicio por proyecto | H7: Sobredesarrollo | I7: Release comercial | J7: Demo auditada
A8: Cliente/promotor | B8: Tash / promotoras | C8: Pipeline de proyectos y arquitectura | D8: Industrialización y ejecución | E8: Llar de Mar 2 preparado | F8: Casos replicables | G8: Margen obra + fees tecnología | H8: Dependencia de un cliente | I8: Contrato/anticipo | J8: Contrato
A9: Mercado | B9: Ayuntamientos/promotoras/constructoras | C9: Demanda local y proyectos | D9: Oferta integral CUEVA/OADAC | E9: Salida comercial septiembre | F9: Embudo comercial estable | G9: Servicios + implementación + licencias | H9: Baja conversión | I9: CRM semanal | J9: CRM

Sheet 15_Mapa_Relaciones
A1: Mapa de relaciones estratégicas
A2: Relaciones separadas por naturaleza: cliente, socio, proveedor, certificador, industrial, canal
A4: Actor | B4: Tipo relación | C4: Línea conectada | D4: Responsable CUEVA | E4: Aporta | F4: CUEVA aporta | G4: Estado | H4: Valor estratégico | I4: Riesgo | J4: Siguiente hito | K4: Fecha objetivo
A5: Tash & Partners | B5: Cliente / arquitectura / pipeline | C5: Llar de Mar 2 / proyectos Baleares | D5: Luis + Ángel | E5: Proyectos, arquitectura, promotor | F5: Modelo industrializado y ejecución OADAC | G5: Activo | H5: Muy alto | I5: Dependencia comercial | J5: Definir Llar de Mar 2 | K5: Q4-26
A6: Valeriano Alles | B6: Partner industrial local | C6: Hub Menorca | D6: Luis | E6: Instalaciones y medios industriales | F6: Tecnología, método, operación | G6: Activo | H6: Muy alto | I6: Acuerdo no formalizado | J6: Firmar marco hub | K6: Q3-26
A7: Medhi / Bini Aida | B7: Partner personal / socio OADAC | C7: Menorca / montaje / terminaciones | D7: Luis + Ángel | E7: Personal y capacidad ejecución | F7: Participación 8% OADAC + proyectos | G7: Pendiente pacto | H7: Muy alto | I7: Gobierno societario | J7: Formalizar 8% | K7: Q3-26
A8: Logistik / José Luis Campos | B8: Cliente industrial / posible socio | C8: CUEVA OS industrial | D8: Luis + Ángel | E8: Capacidad industrial y mercado | F8: Software, método, trazabilidad | G8: Negociación | H8: Muy alto | I8: Mezclar socio/cliente | J8: Oferta cliente separada | K8: Q4-26
A9: KIWA | B9: Certificadora / partner SaaS materia | C9: RMOOB / proyectos 450k + 800k | D9: Luis / Hernán | E9: SaaS materia, certificación, legitimidad | F9: SaaS producto, DPP/POI | G9: Objetivo | H9: Muy alto | I9: Contrato complejo | J9: LOI y alcance | K9: Q1-27
A10: RMOOB TraceLoop | B10: Consorcio / infraestructura | C10: LIFE / infraestructura | D10: Luis | E10: Tracción UE, consorcio, casos | F10: Producto CUEVA infraestructura | G10: Activo | H10: Alto | I10: Ritmo institucional | J10: Plan técnico | K10: Q4-26
A11: Plastic People | B11: Partner material/plástico | C11: Moolde | D11: Luis / Hernán | E11: Material reciclado, circularidad | F11: Producto CUEVA, sensórica, modelo | G11: Activo | H11: Alto | I11: Piloto sin caja | J11: Cofinanciación | K11: Q1-27
A12: Calaf | B12: Constructora / piloto | C12: Moolde | D12: Luis | E12: Obra/piloto constructivo | F12: Encofrado inteligente y trazabilidad | G12: Activo | H12: Alto | I12: Alcance difuso | J12: Presupuesto piloto | K12: Q1-27
A13: Marsam | B13: Marca producto construcción | C13: Prototipos comerciales | D13: Emilio / Luis | E13: Producto alto valor | F13: CUEVA OS, DPP, prototipo | G13: Objetivo | H13: Medio | I13: Prototipo gratis | J13: Oferta pagada | K13: Q2-27
A14: Promotoras / aytos / constructoras | B14: Clientes canal | C14: Comercial general | D14: Emilio Torres | E14: Demanda y proyectos | F14: Oferta industrializada | G14: Prospección | H14: Alto | I14: Baja conversión | J14: CRM + reuniones | K14: Sep-26

Sheet 16_Mapa_Estrategico
A1: Mapa estratégico
A2: De capital mínimo a sostenibilidad: activos, producto, mercado y caja
A4: Pilar estratégico | B4: Contenido | C4: Responsable | D4: Hito de validación
A5: Producto digital | B5: CUEVA OS, DPP, POI, interfaces, IA, telecom, cloud | C5: Hernán / Santi | D5: Release comercial + demos auditables
A6: Operación industrial | B6: Hub OADAC-Valeriano, Medhi personal, Llar de Mar 2 | C6: Luis / Medhi / Valeriano | D6: Nodo Menorca operativo
A7: Mercado y ventas | B7: Tash, Logistik, ayuntamientos, promotoras, constructoras, Marsam | C7: Luis / Ángel / Emilio / Jacqueline | D7: Pipeline > 2,1M objetivo 2027
A8: Certificación / legitimidad | B8: KIWA, RMOOB, LIFE, SaaS materia + producto | C8: Luis / Hernán | D8: Proyectos 450k + 800k
A11: KPIs estratégicos mínimos a diciembre 2027
A12: KPI | B12: Objetivo | C12: Fecha | D12: Propietario | E12: Evidencia
A13: Facturación 2027 | B13: >= 2,1M€ objetivo | C13: Dic-27 | D13: Dirección | E13: Contratos/facturas
A14: EBITDA 2027 | B14: Positivo anual y Q4 autosostenible | C14: Dic-27 | D14: Finanzas | E14: P&L
A15: Clientes/proyectos activos | B15: >= 5 líneas facturables | C15: Dic-27 | D15: Comercial | E15: CRM/contratos
A16: Release CUEVA OS | B16: Entrega comercial estable | C16: Sep-26 | D16: Hernán/Santi | E16: Demo/QA
A17: Valor empresa | B17: Rango 8-12M€; objetivo 9,5M€ | C17: Dic-27 | D17: Dirección | E17: Informe valoración

Sheet 17_Valor_Activos
A1: Valor de activos CUEVA/OADAC
A2: Activos tangibles, intangibles, relacionales y de validación. No confundir coste con valor de mercado.
A4: Activo | B4: Tipo | C4: Valor actual razonado (€) | D4: Valor objetivo fin 2027 (€) | E4: Método / justificación | F4: Dependencias | G4: Evidencia | H4: Riesgo | I4: Responsable | J4: Estado
A5: CUEVA OS / software base | B5: Intangible tecnológico | C5: 900000 | D5: 2200000 | E5: Desarrollo acumulado + producto comercial + multi-cliente | F5: Release estable | G5: Repos, demos, documentación | H5: Dependencia equipo técnico | I5: Hernán | J5: Activo
A6: DPP/POI/trazabilidad campo | B6: Intangible + know-how | C6: 600000 | D6: 1400000 | E6: Validación Menorca/Piedrahita + hardware + metodología | F6: Casos y lecturas | G6: Piedrahita/Menorca/KIWA | H6: Commoditización | I6: Luis/Hernán | J6: Activo
A7: Casos reales Menorca/Piedrahita | B7: Activo comercial | C7: 500000 | D7: 1100000 | E7: Prueba industrial y vivienda como casos de venta | F7: Documentación visual y técnica | G7: Fotos, métricas, contratos | H7: No documentar | I7: Luis/Jacqueline | J7: En marcha
A8: Relaciones estratégicas | B8: Relacional | C8: 700000 | D8: 1900000 | E8: Tash, Valeriano, Medhi, Logistik, KIWA, RMOOB | F8: Contratos/LOI | G8: Mapa relaciones | H8: Dependencia personas | I8: Luis/Ángel | J8: Activo
A9: Modelo Hub OADAC | B9: Operativo/industrial | C9: 400000 | D9: 1300000 | E9: Capacidad replicable de nodo licenciatario | F9: Acuerdo Valeriano/Medhi | G9: Contrato hub | H9: Sobrecoste | I9: Luis | J9: Objetivo
A10: Marca / narrativa / mercado | B10: Marca/comercial | C10: 300000 | D10: 800000 | E10: Salida comercial y posicionamiento categoría | F10: Marketing septiembre | G10: Web/deck/PR | H10: Mensaje débil | I10: Jacqueline | J10: Pendiente
A11: Pipeline 2027 | B11: Comercial | C11: 600000 | D11: 2200000 | E11: Ingresos objetivo con hitos y contratos a formalizar | F11: Firmas y cobros | G11: CRM/facturas | H11: No convertir | I11: Dirección | J11: Objetivo
A12: TOTAL / puente activos | C12: =SUM(C5:C11) | D12: =SUM(D5:D11)

Sheet 18_Valor_Empresa_2027
A1: Valor empresa a cierre 2027
A2: Bridge desde 4M€ actuales hasta objetivo 9,5M€ con objetivos cumplidos
A4: Componente | B4: Valor incremental (€) | C4: Valor acumulado (€) | D4: Base de cálculo | E4: Evidencia requerida | F4: Riesgo | G4: Estado | H4: Comentario | I4: Responsable | J4: Fecha
A5: Valor actual de referencia | B5: 0 | C5: 4000000 | D5: Inversión histórica acumulada / valoración interna actual | E5: Memoria de inversión y activos | F5: Soporte insuficiente | G5: Base | H5: Punto de partida definido por dirección | I5: Dirección | J5: Jul-26
A6: Producto CUEVA OS comercializable | B6: 1200000 | C6: =C5+B6 | D6: Release, demos, arquitectura, licencias, seguridad | E6: Demo + docs + QA | F6: No estabilizar producto | G6: Objetivo | H6: Software/IT reforzado con 78k | I6: Hernán/Santi | J6: Sep-26
A7: Casos y validación industrial | B7: 900000 | C7: =C6+B7 | D7: Piedrahita terminado + Llar de Mar 2 + Menorca | E7: Casos visuales/técnicos | F7: No cerrar casos | G7: Objetivo | H7: De TRL 7-8 a validación comercial | I7: Luis/Jacqueline | J7: Q2-27
A8: Hub OADAC operativo | B8: 800000 | C8: =C7+B8 | D8: Valeriano + Medhi + showroom + proceso replicable | E8: Acuerdos y visitas | F8: Sobrecoste / informalidad | G8: Objetivo | H8: Licenciatario operativo Baleares | I8: Luis | J8: Q2-27
A9: Pipeline e ingresos 2027 | B9: 1500000 | C9: =C8+B9 | D9: Ingresos objetivo >2,1M€ y EBITDA positivo | E9: Contratos/facturas/P&L | F9: No convertir pipeline | G9: Objetivo | H9: Principal driver de valoración | I9: Dirección | J9: Dic-27
A10: Alianza KIWA/RMOOB certificación | B10: 900000 | C10: =C9+B10 | D10: SaaS materia + producto + certificación | E10: LOI/contratos KIWA | F10: Dependencia externa | G10: Objetivo | H10: Posiciona a CUEVA en certificación y trazabilidad | I10: Luis/Hernán | J10: Dic-27
A11: Valor relacional/mercado | B11: 200000 | C11: =C10+B11 | D11: Tash/Logistik/Marsam/promotoras/aytos | E11: CRM y acuerdos | F11: Dependencia personal | G11: Objetivo | H11: Red comercial y partners | I11: Luis/Ángel/Emilio | J11: Dic-27
A12: VALOR OBJETIVO FIN 2027 | C12: =C11 | D12: Rango razonado: 8M€ - 12M€; objetivo interno 9,5M€ | E12: Informe valoración | F12: Necesita soporte externo | G12: Objetivo | H12: No es valoración independiente | I12: Dirección | J12: Dic-27

Sheet 19_Roadmap_Visual
A1: Roadmap visual 2026-2027
A2: Vista de hitos por semestre y línea estratégica
A4: Línea | B4: Jul-26 | C4: Ago-26 | D4: Sep-26 | E4: Oct-26 | F4: Nov-26 | G4: Dic-26 | H4: Q1-27 | I4: Q2-27 | J4: Q3-27 | K4: Q4-27 | L4: Responsable | M4: Gate | N4: Evidencia | O4: Riesgo | P4: Estado
A5: Deuda / saneamiento | B5: Medhi, Apellicer, Ferzohaus | C5: Pagos y acuerdos | D5: Piedrahita cierre | L5: Luis/Ángel | M5: Acuerdos firmados | N5: Recibos/contratos | O5: Arrastre deuda | P5: Activo
A6: Piedrahita | B6: Interiores/saneamientos | C6: Remates | D6: Entrega/caso | L6: Luis/Jorge | M6: Entrega mediados sep | N6: Fotos/ficha caso | O6: Retraso | P6: En marcha
A7: Producto CUEVA OS | B7: Backlog release | C7: Infra/telecom | D7: Demo comercial | E7: QA | F7: Documentación | G7: Entrega estable | H7: Logistik setup | I7: KIWA prep | J7: SaaS recurrente | K7: Escalado | L7: Hernán/Santi | M7: Release estable | N7: Demo/QA logs | O7: Fragilidad técnica | P7: Activo
A8: Marketing / comercial | B8: Plan | C8: Assets | D8: Salida mercado | E8: CRM | F8: Reuniones | G8: Oferta base | H8: Campañas | I8: Conversión | J8: Casos | K8: ARR/PR | L8: Jacqueline/Emilio | M8: Web+CRM | N8: Web/CRM | O8: Poca conversión | P8: Pendiente
A9: Hub OADAC Menorca | B9: Marco Valeriano | C9: Layout | D9: Fase 0-1 | E9: Showroom mínimo | F9: Pipeline | G9: Plan 2027 | H9: Llar de Mar 2 | I9: Nodo operativo | J9: Visitas/clientes | K9: Optimización | L9: Luis/Medhi | M9: Contrato hub | N9: Fotos/acuerdo | O9: Sobrecoste | P9: Activo
A10: Llar de Mar 2 | E10: Preparación | F10: Presupuesto | G10: Contrato/anticipo | H10: Ejecución/cobro | I10: Cierre caso | L10: Luis/Ángel | M10: Contrato | N10: Factura/caso | O10: Margen obra | P10: Objetivo
A11: Logistik | E11: Oferta separada | F11: Demo | G11: LOI cliente | H11: Contrato | I11: Implementación | J11: Despliegue | K11: Cierre 2027 | L11: Luis/Ángel | M11: Cliente antes socio | N11: Contrato | O11: Bloqueo societario | P11: Objetivo
A12: KIWA/RMOOB | E12: Alcance | F12: LOI prep | G12: Plan técnico | H12: Contrato A | I12: Proyecto 450k | J12: B1 400k | K12: B2 400k | L12: Luis/Hernán | M12: LOI + contrato | N12: Contratos/cobros | O12: Dependencia externa | P12: Objetivo
A13: Moolde/Marsam | E13: Alcance | F13: Cofinanciación | G13: Prototipo plan | H13: Contrato piloto | I13: Ejecución | J13: Prototipos | K13: Ventas | L13: Luis/Emilio | M13: Pago previo | N13: Presupuesto | O13: Prototipo gratis | P13: Objetivo

Sheet 20_Riesgos_Gates
A1: Riesgos, gates y checklist audit-ready
A2: Gestión de riesgos por línea y decisión de continuidad por gates
A4: Riesgo | B4: Probabilidad | C4: Impacto | D4: Severidad | E4: Mitigación | F4: Gate de control | G4: Fecha revisión | H4: Responsable | I4: Evidencia | J4: Estado | K4: Decisión si falla | L4: Notas
A5: Capital 300k no se desembolsa completo | B5: Media | C5: Muy alto | D5: Alta | E5: Tramos vinculados a hitos y pagos críticos | F5: Aprobación plan de desembolso | G5: Jul-26 | H5: Dirección | I5: Acuerdo financiación | J5: Pendiente | K5: Parar capex no crítico
A6: Deuda proveedores daña reputación | B6: Media | C6: Alto | D6: Alta | E6: Acuerdos escritos y pagos priorizados | F6: Cierre Medhi/Apellicer/Ferzohaus | G6: Ago-26 | H6: Luis/Ángel | I6: Recibos/acuerdos | J6: Pendiente | K6: No lanzar comercial sin cierre
A7: Piedrahita se retrasa | B7: Media | C7: Alto | D7: Alta | E7: Ring-fence cobros y remates | F7: Entrega mediados septiembre | G7: Sep-26 | H7: Luis/Jorge | I7: Acta/fotos | J7: En marcha | K7: Refuerzo puntual obra
A8: Software no llega estable a salida comercial | B8: Media | C8: Muy alto | D8: Alta | E8: Partida SW/IT reforzada y releases mensuales | F8: Release septiembre | G8: Sep-26 | H8: Hernán/Santi | I8: Demo/QA | J8: Activo | K8: Reducir alcance a MVP vendible
A9: Pipeline 2027 no se convierte | B9: Media | C9: Muy alto | D9: Alta | E9: Separar target/committed, LOI y CRM | F9: Contratos Q1-Q2 | G9: Mar-27 | H9: Dirección | I9: CRM/LOI | J9: Pendiente | K9: Reducir contratación 2027
A10: KIWA/RMOOB se retrasa | B10: Media | C10: Alto | D10: Media-alta | E10: Fasear 450k y 800k en subproyectos | F10: LOI y alcance técnico | G10: Q1-27 | H10: Luis/Hernán | I10: LOI/contrato | J10: Pendiente | K10: No reconocer ingresos hasta firma
A11: Hub Menorca sobredimensiona capex | B11: Media | C11: Medio | D11: Media | E11: Fase 0-1, aprovechar in-kind Valeriano | F11: Gates por contrato | G11: Dic-26 | H11: Luis | I11: Contrato hub | J11: Activo | K11: No liberar fase 2
A12: Valoración fin 2027 no soportada | B12: Media | C12: Alto | D12: Media-alta | E12: Vincular valor a KPIs, ingresos y activos evidenciables | F12: Informe valoración | G12: Dic-27 | H12: Dirección | I12: Informe externo/interno | J12: Pendiente | K12: Usar rango bajo 8M

Sheet 21_Dashboard
A1: Dashboard ejecutivo
A2: Resumen de KPIs, caja, ingresos, valor y gates del BP 300k
A4: Capital mínimo necesario | E4: Uso fondos control | I4: Ingresos objetivo 2027
A5: ='03_Uso_Fondos_300K'!B13 | E5: ='03_Uso_Fondos_300K'!B12 | I5: =SUM('11_Ingresos_2026_2027'!J14:U14)
A8: EBITDA total modelo | E8: Caja final dic-27 | I8: Valor objetivo fin 2027
A9: ='12_Cuenta_Resultados'!T14 | E9: ='13_Caja_Mensual'!S10 | I9: ='18_Valor_Empresa_2027'!C12
A13: Lectura ejecutiva
A14: El BP concentra los 300k en estabilizar equipo, producto, telecomunicaciones, deuda crítica, salida comercial y hub Menorca. 2027 se sostiene por Llar de Mar 2 (535k), Logistik, KIWA/RMOOB 450k y el proyecto KIWA/RMOOB de 800k dividido en dos fases dentro del segundo semestre. La empresa objetivo debe entrar en autosostenibilidad por caja durante 2027, siempre condicionada a contratos, cobros por hitos y control de contratación.
